{
  "fiscalSign": "4115129318",
  "provisionSum": 0.00,
  "user": "АКЦИОНЕРНОЕ ОБЩЕСТВО \"ВКУСВИЛЛ\"",
  "machineNumber": null,
  "fiscalDriveNumber": "7380440902366680",
  "fiscalDocumentFormatVer": "4",
  "totalSum": 3566.61,
  "taxationType": 1,
  "dateTime": "2025-09-28T20:34:00",
  "items": [
    {
      "sum": 198.00,
      "paymentType": 4,
      "nds": 1,
      "providerInn": null,
      "quantity": 1.0,
      "name": "Оливки 'Каламата' без косточки, 120 г",
      "productType": 1,
      "price": 198.00,
      "providerData": null,
      "paymentAgentData": null
    },
    {
      "sum": 508.00,
      "paymentType": 4,
      "nds": 1,
      "providerInn": null,
      "quantity": 4.0,
      "name": "Чипсы Салями",
      "productType": 1,
      "price": 127.00,
      "providerData": null,
      "paymentAgentData": null
    },
    {
      "sum": 257.00,
      "paymentType": 4,
      "nds": 2,
      "providerInn": null,
      "quantity": 1.0,
      "name": "Томаты красные Зира, 450 г",
      "productType": 1,
      "price": 257.00,
      "providerData": null,
      "paymentAgentData": null
    },
    {
      "sum": 263.00,
      "paymentType": 4,
      "nds": 2,
      "providerInn": null,
      "quantity": 1.0,
      "name": "Сосиски куриные из филе грудки 'Легкие'",
      "productType": 1,
      "price": 263.00,
      "providerData": null,
      "paymentAgentData": null
    },
    {
      "sum": 99.00,
      "paymentType": 4,
      "nds": 2,
      "providerInn": null,
      "quantity": 1.0,
      "name": "Хлеб 'Ремесленный с семенами льна и зернами ржи', нарезка",
      "productType": 1,
      "price": 99.00,
      "providerData": null,
      "paymentAgentData": null
    },
    {
      "sum": 677.00,
      "paymentType": 4,
      "nds": 2,
      "providerInn": null,
      "quantity": 1.0,
      "name": "Говядина филей, 550 г",
      "productType": 1,
      "price": 677.00,
      "providerData": null,
      "paymentAgentData": null
    },
    {
      "sum": 197.00,
      "paymentType": 4,
      "nds": 2,
      "providerInn": null,
      "quantity": 1.0,
      "name": "Лук шалот, 250 г",
      "productType": 1,
      "price": 197.00,
      "providerData": null,
      "paymentAgentData": null
    },
    {
      "sum": 287.00,
      "paymentType": 4,
      "nds": 2,
      "providerInn": null,
      "quantity": 1.0,
      "name": "Грудинка запеченная с перцем, нарезка 150 г",
      "productType": 1,
      "price": 287.00,
      "providerData": null,
      "paymentAgentData": null
    },
    {
      "sum": 116.00,
      "paymentType": 4,
      "nds": 1,
      "providerInn": null,
      "quantity": 1.0,
      "name": "Морковь кубиками зам.",
      "productType": 1,
      "price": 116.00,
      "providerData": null,
      "paymentAgentData": null
    },
    {
      "sum": 362.00,
      "paymentType": 4,
      "nds": 2,
      "providerInn": null,
      "quantity": 1.0,
      "name": "Колбаса из говядины категории А, с.к, нарезка",
      "productType": 1,
      "price": 362.00,
      "providerData": null,
      "paymentAgentData": null
    },
    {
      "sum": 48.00,
      "paymentType": 4,
      "nds": 1,
      "providerInn": null,
      "quantity": 1.0,
      "name": "Чеснок сушеный молотый",
      "productType": 1,
      "price": 48.00,
      "providerData": null,
      "paymentAgentData": null
    },
    {
      "sum": 141.00,
      "paymentType": 4,
      "nds": 1,
      "providerInn": null,
      "quantity": 1.0,
      "name": "Огурцы соленые, 400 г",
      "productType": 1,
      "price": 141.00,
      "providerData": null,
      "paymentAgentData": null
    },
    {
      "sum": 188.00,
      "paymentType": 4,
      "nds": 2,
      "providerInn": null,
      "quantity": 1.0,
      "name": "Грудка куриная копчено-вареная",
      "productType": 1,
      "price": 188.00,
      "providerData": null,
      "paymentAgentData": null
    },
    {
      "sum": 8.00,
      "paymentType": 4,
      "nds": 1,
      "providerInn": null,
      "quantity": 1.0,
      "name": "Пакет-майка 'ВкусВилл' малый",
      "productType": 1,
      "price": 8.00,
      "providerData": null,
      "paymentAgentData": null
    },
    {
      "sum": 133.00,
      "paymentType": 4,
      "nds": 2,
      "providerInn": null,
      "quantity": 1.0,
      "name": "Пампушки с чесноком, 3 шт",
      "productType": 1,
      "price": 133.00,
      "providerData": null,
      "paymentAgentData": null
    },
    {
      "sum": 29.14,
      "paymentType": 4,
      "nds": 2,
      "providerInn": null,
      "quantity": 0.62,
      "name": "Лук репчатый",
      "productType": 1,
      "price": 47.00,
      "providerData": null,
      "paymentAgentData": null
    },
    {
      "sum": 55.47,
      "paymentType": 4,
      "nds": 2,
      "providerInn": null,
      "quantity": 0.215,
      "name": "Лимоны",
      "productType": 1,
      "price": 258.00,
      "providerData": null,
      "paymentAgentData": null
    }
  ],
  "userInn": "7734443270  ",
  "fiscalDocumentNumber": 225612,
  "retailPlace": "www.vkusvill.ru",
  "retailPlaceAddress": "г. Москва, Остаповский проезд, д.22, стр.16",
  "cashTotalSum": 0.00,
  "prepaidSum": 3566.61,
  "kktRegId": "0006207493055699    ",
  "paymentAgentType": null,
  "requestNumber": 1944,
  "nds10": 231.60,
  "messageFiscalSign": null,
  "shiftNumber": 149,
  "fnsSite": null,
  "ecashTotalSum": 0.00,
  "operationType": 1,
  "creditSum": 0.00,
  "nds18": 169.83,
  "receiptCode": null,
  "buyerAddress": "abakumovoleg@gmail.com",
  "operator": "Кассир",
  "internetSign": 1,
  "nds0": null,
  "ndsNo": null,
  "nds18118": null,
  "nds10110": null,
  "amountsReceiptNds": null
}